<?xml version="1.0"?>
<object xmlns:xsi="http://www.w3.org/2001/XMLSchema-instance" xmlns:xsd="http://www.w3.org/2001/XMLSchema" xsi:type="generic">
  <type>obj_t_weapon</type>
  <id subtype="Permanent" asGuid="51EC7078-A0BB-4B89-B618-84153D51C9F7" />
  <protoId subtype="Prototype" align="65535" unk="-2113312566" asPrototype="4060">
    <asBytes>3A8AAAIAAAAAAAAAiW06HQ==</asBytes>
  </protoId>
  <protoHandle />
  <field40>6</field40>
  <typeGroup>Item</typeGroup>
  <typeGroupParent>Common</typeGroupParent>
  <Props>
    <prop field="obj_f_location" fieldType="Int64" asLoc="449,540" />
    <prop field="obj_f_flags" fieldType="Int32">
      <asObjectFlags>
        <ObjectFlag>OF_FLAT</ObjectFlag>
        <ObjectFlag>OF_SEE_THROUGH</ObjectFlag>
        <ObjectFlag>OF_SHOOT_THROUGH</ObjectFlag>
        <ObjectFlag>OF_NO_BLOCK</ObjectFlag>
        <ObjectFlag>OF_INVENTORY</ObjectFlag>
        <ObjectFlag>OF_HEIGHT_SET</ObjectFlag>
        <ObjectFlag>OF_RADIUS_SET</ObjectFlag>
      </asObjectFlags>
    </prop>
    <prop field="obj_f_radius" fieldType="Float32" asFloat="24.0085583" />
    <prop field="obj_f_3d_render_height" fieldType="Float32" asFloat="1.580546" />
    <prop field="obj_f_item_parent" fieldType="Obj">
      <value xsi:type="ObjectId" subtype="Permanent" asGuid="DA949FBF-8D39-4E9F-8CFA-45B6D92627A4" />
    </prop>
    <prop field="obj_f_item_inv_location" fieldType="Int32" asInt="9" />
  </Props>
  <Location x="449" y="540" />
</object>